{
    "$schema": "http://json-schema.org/draft-07/schema#",
    "$id": "http://example.com/historyCreate.json",
    "type": "object",
    "properties": {
      "weightUsed": {
        "type": "integer",
        "minimum": 0,
        "maximum": 1500
      },
      "numSets": {
        "type": "integer",
        "minimum": 0,
        "maximum": 100
      },
      "numReps": {
        "type": "integer",
        "minimum": 0,
        "maximum": 100
      }
    },
    "additionalProperties": false,
    "required": []
}